gitlab_changelog_gen/__init__.py
gitlab_changelog_gen/changelog.py
gitlab_changelog_gen/cmd.py
gitlab_changelog_gen/config.py
gitlab_changelog_gen/generator.py
gitlab_changelog_gen-0.0.3.dist-info/LICENSE
gitlab_changelog_gen-0.0.3.dist-info/METADATA
gitlab_changelog_gen-0.0.3.dist-info/WHEEL
gitlab_changelog_gen-0.0.3.dist-info/entry_points.txt
gitlab_changelog_gen-0.0.3.dist-info/top_level.txt
gitlab_changelog_gen-0.0.3.dist-info/RECORD
