Metadata-Version: 2.1
Name: gitlab-changelog-gen
Version: 0.0.3
Summary: A command line utility to generate CHANGELOG.md with Gitlab merge requests
Home-page: https://github.com/tossmilestone/gitlab-changelog-gen
Author: tossmilestone
Author-email: tossmilestone@gmail.com
License: MIT
Keywords: gitlab changelog python
Platform: UNKNOWN
Classifier: Environment :: Console
Classifier: Programming Language :: Python
Classifier: Programming Language :: Python :: 3.6
Classifier: Programming Language :: Python :: 3.7
Classifier: Programming Language :: Python :: 3 :: Only
Classifier: Topic :: Software Development :: Libraries :: Python Modules
Classifier: License :: OSI Approved :: MIT License
Classifier: Operating System :: OS Independent
Requires-Dist: python-gitlab (>=1.10.0)
Requires-Dist: pyyaml (>=5.1)
